aerofoils/__init__.py
aerofoils/aerofoils.py
aerofoils/cli.py
aerofoils-0.1.1.dist-info/AUTHORS.rst
aerofoils-0.1.1.dist-info/LICENSE
aerofoils-0.1.1.dist-info/METADATA
aerofoils-0.1.1.dist-info/WHEEL
aerofoils-0.1.1.dist-info/entry_points.txt
aerofoils-0.1.1.dist-info/top_level.txt
aerofoils-0.1.1.dist-info/RECORD
