Metadata-Version: 2.1
Name: aerofoils
Version: 0.1.1
Summary: Aerofoil Design Toolkit
Home-page: https://github.com/ltiao/aerofoils
Author: Louis Tiao
Author-email: louistiao@gmail.com
License: MIT license
Keywords: aerofoils
Classifier: Development Status :: 2 - Pre-Alpha
Classifier: Intended Audience :: Developers
Classifier: License :: OSI Approved :: MIT License
Classifier: Natural Language :: English
Classifier: Programming Language :: Python :: 3
Classifier: Programming Language :: Python :: 3.6
Classifier: Programming Language :: Python :: 3.7
Classifier: Programming Language :: Python :: 3.8
Requires-Python: >=3.6
License-File: LICENSE
License-File: AUTHORS.rst
Requires-Dist: Click (>=7.0)
